examples/read_imu/read_imu.py
examples/spin_motors/spin_motors.py
motorgo/__init__.py
motorgo/brushed_motor_channel.py
motorgo/common.py
motorgo/imu.py
motorgo/message_parser.py
motorgo/messages.py
motorgo/plink.py
motorgo/version.py
motorgo/cli/__init__.py
motorgo/cli/board_comms_utils.py
motorgo/cli/cli.py
motorgo/cli/flash_utils.py
motorgo_firmware/get_version.py
motorgo_python-0.1.0.dist-info/METADATA
motorgo_python-0.1.0.dist-info/WHEEL
motorgo_python-0.1.0.dist-info/entry_points.txt
motorgo_python-0.1.0.dist-info/top_level.txt
motorgo_python-0.1.0.dist-info/RECORD
