Metadata-Version: 2.2
Name: motorgo-python
Version: 0.1.0
Summary: Python API for the Raspberry Pi + MotorGo line.
Author-email: Swapnil Pande <swapnil@everyflavor.bot>
License: GPL-3.0-only
Project-URL: Homepage, https://github.com/Every-Flavor-Robotics/motorgo-python
Classifier: Development Status :: 4 - Beta
Classifier: License :: OSI Approved :: GNU General Public License v3 (GPLv3)
Classifier: Operating System :: POSIX :: Linux
Classifier: Programming Language :: Python :: 3
Requires-Python: >=3.6
Requires-Dist: spidev
Requires-Dist: gpiozero
Requires-Dist: RPi.GPIO
Requires-Dist: numpy
Requires-Dist: imufusion
